Workbook
Name NativeTimeline_Month: #N/A
Name Slicer_Category: #N/A
Name Slicer_Channel: #N/A
Name Slicer_Product: #N/A
Name Slicer_Region: #N/A

Sheet Dataset
A1: Order ID | B1: Date | C1: Product | D1: Region | E1: Channel | F1: Salesperson | G1: Quantity | H1: Category | I1: Unit Price | J1: Discount % | K1: Revenue | L1: Month
A2: ORD-0175 | B2: 45658 | C2: Tablet | D2: West | E2: Online | F2: Diya | G2: 5 | H2: Electronics | I2: 26000 | J2: 0.05 | K2: 123500 | L2: 45658
A3: ORD-0183 | B3: 45659 | C3: Desk | D3: North | E3: Store | F3: Aarav | G3: 4 | H3: Furniture | I3: 12500 | J3: 0 | K3: 50000 | L3: 45658
A4: ORD-0116 | B4: 45659 | C4: Headphones | D4: West | E4: Online | F4: Rohan | G4: 1 | H4: Accessories | I4: 2800 | J4: 0.1 | K4: 2520 | L4: 45658
A5: ORD-0024 | B5: 45660 | C5: Headphones | D5: East | E5: Online | F5: Kabir | G5: 3 | H5: Accessories | I5: 2800 | J5: 0.05 | K5: 7980 | L5: 45658
A6: ORD-0327 | B6: 45662 | C6: Keyboard | D6: North | E6: Store | F6: Anaya | G6: 2 | H6: Accessories | I6: 1900 | J6: 0.1 | K6: 3420 | L6: 45658
A7: ORD-0091 | B7: 45663 | C7: Keyboard | D7: West | E7: Store | F7: Rohan | G7: 5 | H7: Accessories | I7: 1900 | J7: 0 | K7: 9500 | L7: 45658
A8: ORD-0030 | B8: 45666 | C8: Office Chair | D8: East | E8: Online | F8: Kabir | G8: 4 | H8: Furniture | I8: 9200 | J8: 0.05 | K8: 34960 | L8: 45658
A9: ORD-0170 | B9: 45666 | C9: Laptop | D9: East | E9: Online | F9: Rohan | G9: 1 | H9: Electronics | I9: 58000 | J9: 0 | K9: 58000 | L9: 45658
A10: ORD-0171 | B10: 45668 | C10: Headphones | D10: West | E10: Online | F10: Diya | G10: 6 | H10: Accessories | I10: 2800 | J10: 0.05 | K10: 15960 | L10: 45658
A11: ORD-0346 | B11: 45669 | C11: Keyboard | D11: East | E11: Online | F11: Aarav | G11: 4 | H11: Accessories | I11: 1900 | J11: 0.1 | K11: 6840 | L11: 45658
A12: ORD-0414 | B12: 45670 | C12: Monitor | D12: West | E12: Store | F12: Meera | G12: 4 | H12: Electronics | I12: 14500 | J12: 0 | K12: 58000 | L12: 45658
A13: ORD-0293 | B13: 45674 | C13: Monitor | D13: West | E13: Store | F13: Aarav | G13: 5 | H13: Electronics | I13: 14500 | J13: 0 | K13: 72500 | L13: 45658
... A421: ORD-0115 | B421: 46202 | C421: Desk | D421: East | E421: Online | F421: Anaya | G421: 5 | H421: Furniture | I421: 12500 | J421: 0 | K421: 62500 | L421: 46174

Sheet Analysis
A1: RETAIL SALES DATA ANALYSIS
A5: Metric | B5: Value | D5: Row Labels | E5: Sum of Revenue | G5: Row Labels | H5: Sum of Revenue
A6: Total Revenue | B6: =SUM(Dataset!K2:K421) -> 21574592 | D6: Laptop | E6: 11771100 | G6: Electronics | H6: 16718525
A7: Total Orders | B7: =COUNTA(Dataset!A2:A421) -> 420 | D7: Tablet | E7: 2707900 | G7: Furniture | H7: 3849970
A8: Total Units Sold | B8: =SUM(Dataset!G2:G421) -> 1484 | D8: Monitor | E8: 2239525 | G8: Accessories | H8: 1006097.5
A9: Average Order Value | B9: =AVERAGE(Dataset!K2:K421) -> 51368.077 | D9: Desk | E9: 1983750 | G9: Grand Total | H9: 21574592
A10: Top product by revenue | B10: Laptop | D10: Office Chair | E10: 1866220
A11: Top category by revenue | B11: Electronics | D11: Headphones | E11: 492940 | G11: Row Labels | H11: Sum of Revenue
A12: Category with highest revenue % | B12: =(GETPIVOTDATA("Revenue",$G$5,"Category","Electronics")/B6)*100 -> 77.49173 | D12: Keyboard | E12: 324330 | G12: North | H12: 6230462.5
A13: Top region by revenue | B13: North | D13: Mouse | E13: 188827.5 | G13: West | H13: 6146122.5
A14: Region with highest revenue % | B14: =(GETPIVOTDATA("Revenue",$G$11,"Region","North")/B6)*100 -> 28.878703 | D14: Grand Total | E14: 21574592 | G14: South | H14: 5438250
A15: Top channel by revenue | B15: Online | G15: East | H15: 3759757.5
A16: Highest Revenue Month | B16: 45962 | G16: Grand Total | H16: 21574592
A18: Monthly Revenue | G18: Row Labels | H18: Sum of Revenue
A19: 45658 | B19: =SUMIF(Dataset!L2:L421,Analysis!$A19,Dataset!K2:K421) -> 839380 | G19: Online | H19: 14125438
A20: 45689 | B20: =SUMIF(Dataset!L3:L422,Analysis!$A20,Dataset!K3:K422) -> 1086050 | G20: Store | H20: 7449155
A21: 45717 | B21: =SUMIF(Dataset!L4:L423,Analysis!$A21,Dataset!K4:K423) -> 1667882.5 | G21: Grand Total | H21: 21574592
A22: 45748 | B22: =SUMIF(Dataset!L5:L424,Analysis!$A22,Dataset!K5:K424) -> 1481695
A23: 45778 | B23: =SUMIF(Dataset!L6:L425,Analysis!$A23,Dataset!K6:K425) -> 677430
A24: 45809 | B24: =SUMIF(Dataset!L7:L426,Analysis!$A24,Dataset!K7:K426) -> 1388460
A25: 45839 | B25: =SUMIF(Dataset!L8:L427,Analysis!$A25,Dataset!K8:K427) -> 869435
A26: 45870 | B26: =SUMIF(Dataset!L9:L428,Analysis!$A26,Dataset!K9:K428) -> 1144485
A27: 45901 | B27: =SUMIF(Dataset!L10:L429,Analysis!$A27,Dataset!K10:K429) -> 1283345
A28: 45931 | B28: =SUMIF(Dataset!L11:L430,Analysis!$A28,Dataset!K11:K430) -> 1423987.5
A29: 45962 | B29: =SUMIF(Dataset!L12:L431,Analysis!$A29,Dataset!K12:K431) -> 1847780
A30: 45992 | B30: =SUMIF(Dataset!L13:L432,Analysis!$A30,Dataset!K13:K432) -> 1231547.5
A31: 46023 | B31: =SUMIF(Dataset!L14:L433,Analysis!$A31,Dataset!K14:K433) -> 939220
A32: 46054 | B32: =SUMIF(Dataset!L15:L434,Analysis!$A32,Dataset!K15:K434) -> 1056920
A33: 46082 | B33: =SUMIF(Dataset!L16:L435,Analysis!$A33,Dataset!K16:K435) -> 1175567.5
... A36: 46174 | B36: =SUMIF(Dataset!L19:L438,Analysis!$A36,Dataset!K19:K438) -> 986380
A37: Total Revenue | B37: =SUM(B19:B36) -> 21574592

Sheet Product vs Revenue
A3: Row Labels | B3: Sum of Revenue
A4: Laptop | B4: 11771100
A5: Tablet | B5: 2707900
A6: Monitor | B6: 2239525
A7: Desk | B7: 1983750
A8: Office Chair | B8: 1866220
A9: Headphones | B9: 492940
A10: Keyboard | B10: 324330
A11: Mouse | B11: 188827.5
A12: Grand Total | B12: 21574592

Sheet Category vs Revenue
A3: Row Labels | B3: Sum of Revenue
A4: Electronics | B4: 16718525
A5: Furniture | B5: 3849970
A6: Accessories | B6: 1006097.5
A7: Grand Total | B7: 21574592

Sheet Region vs Revenue
A3: Row Labels | B3: Sum of Revenue
A4: East | B4: 3759757.5
A5: North | B5: 6230462.5
A6: South | B6: 5438250
A7: West | B7: 6146122.5
A8: Grand Total | B8: 21574592

Sheet Channel vs Revenue
A3: Row Labels | B3: Sum of Revenue
A4: Online | B4: 14125438
A5: Store | B5: 7449155
A6: Grand Total | B6: 21574592

Sheet Monthly Revenue
A3: Row Labels | B3: Sum of Revenue
A4: Jan
A5: 2025 | B5: 839380
A6: 2026 | B6: 939220
A7: Feb
A8: 2025 | B8: 1086050
A9: 2026 | B9: 1056920
A10: Mar
A11: 2025 | B11: 1667882.5
A12: 2026 | B12: 1175567.5
A13: Apr
A14: 2025 | B14: 1481695
A15: 2026 | B15: 1078382.5
A16: May
A17: 2025 | B17: 677430
A18: 2026 | B18: 1396645
A19: Jun
A20: 2025 | B20: 1388460
A21: 2026 | B21: 986380
A22: Jul
A23: 2025 | B23: 869435
A24: Aug
A25: 2025 | B25: 1144485
A26: Sep
A27: 2025 | B27: 1283345
A28: Oct
A29: 2025 | B29: 1423987.5
A30: Nov
A31: 2025 | B31: 1847780
A32: Dec
A33: 2025 | B33: 1231547.5
A34: Grand Total | B34: 21574592

Sheet Dashboard
A1: RETAIL SALES DASHBOARD
